{
    "translations": {
        "de": { 
            "Plex IP-Adress": "Plex IP-Adresse",
            "UpdateTimer": "Aktualisierungsintervall",
            "Minutes": "Minuten",
            "Update successed": "Update erfolgreich",
            "Port is not numeric": "Port ist nicht numerisch",
            "Port is larger then five digits": "Port hat mehr als f체nf Ziffern",
            "Port is lager den maximal port number": "Port ist l채nger als erlaubt",
            "No IPV4 Ip-Adress": "Keine g체ltige IPV4 Adresse",
            "Host not aviable": "Host ist nicht erreichbar",
            "Update": "Aktualisieren",
            "Update Button Color":  "Farbe Aktualisierungsbutton",
            "Green": "Gr체n",
            "Orange": "Orange",
            "Yellow": "Gelb",
            "Red": "Rot",
            "Blue": "Blau",
            "URL is not reachable": "URL ist nicht erreichbar",
            "Bibliothek": "Bibliothek",
            "Bibliothek Type": "Bibliotheks Typ",
            "Bibliothek ID": "Bibliotheks ID", 
            "Last Update": "Letzte Aktualisierung",
            "Update Mediathek": "Aktualisierung Mediathek"
        }
    }
}